odoo/addons/partner_title_active/README.rst
odoo/addons/partner_title_active/__init__.py
odoo/addons/partner_title_active/__manifest__.py
odoo/addons/partner_title_active/i18n/it.po
odoo/addons/partner_title_active/i18n/partner_title_active.pot
odoo/addons/partner_title_active/models/__init__.py
odoo/addons/partner_title_active/models/res_partner_title.py
odoo/addons/partner_title_active/readme/CONTRIBUTORS.md
odoo/addons/partner_title_active/static/description/icon.png
odoo/addons/partner_title_active/tests/__init__.py
odoo/addons/partner_title_active/tests/test_partner_title.py
odoo/addons/partner_title_active/views/res_partner_title.xml
odoo_addon_partner_title_active-18.0.1.0.0.1.dist-info/METADATA
odoo_addon_partner_title_active-18.0.1.0.0.1.dist-info/WHEEL
odoo_addon_partner_title_active-18.0.1.0.0.1.dist-info/top_level.txt
odoo_addon_partner_title_active-18.0.1.0.0.1.dist-info/RECORD
